refugue/__init__.py
refugue/_print_version.py
refugue/_version.py
refugue/cli.py
refugue/cli.py~
refugue/defaults.py
refugue/defaults.py~
refugue/image.py
refugue/image.py~
refugue/main.py~
refugue/network.py
refugue/network.py~
refugue/sync.py
refugue/sync.py~
refugue/util.py
refugue/configs/__init__.py
refugue/configs/config.py
refugue/configs/config.py~
refugue/protocols/__init__.py
refugue/protocols/rsync.py
refugue/protocols/rsync.py~
refugue-0.0.1a3.dev0.dist-info/AUTHORS.org
refugue-0.0.1a3.dev0.dist-info/LICENSE
refugue-0.0.1a3.dev0.dist-info/METADATA
refugue-0.0.1a3.dev0.dist-info/WHEEL
refugue-0.0.1a3.dev0.dist-info/entry_points.txt
refugue-0.0.1a3.dev0.dist-info/top_level.txt
refugue-0.0.1a3.dev0.dist-info/RECORD
