Metadata-Version: 2.1
Name: refugue
Version: 0.0.1a3.dev0
Summary: Manage data working sets between computers and drives
Home-page: https://github.com/salotz/refugue
Author: Samuel D. Lotz
Author-email: samuel.lotz@salotz.info
License: MIT
Platform: UNKNOWN
Classifier: Topic :: Utilities
Classifier: License :: OSI Approved :: MIT License
Classifier: Programming Language :: Python :: 3
Requires-Dist: invoke
Requires-Dist: click
Requires-Dist: fabric
Requires-Dist: toml
Requires-Dist: py-rsync
Provides-Extra: all
